{"challenge": {"areResultsFinal": true, "endMs": 1402763400000, "id": "000000000043371f", "isPracticeAvailable": true, "resultStatus": 30, "resultStatusStr": "FINALIZED", "startMs": 1402754400000, "tasks": [{"id": "00000000004331cb", "numAttempted": 236, "tests": [{"numSolved": 140, "type": 1, "typeStr": "VISIBLE", "value": 12}, {"numSolved": 16, "type": 2, "typeStr": "HIDDEN", "value": 22}], "title": "Crime House"}, {"id": "00000000004336d0", "numAttempted": 81, "tests": [{"numSolved": 60, "type": 1, "typeStr": "VISIBLE", "value": 15}, {"numSolved": 0, "type": 2, "typeStr": "HIDDEN", "value": 24}], "title": "Willow"}, {"id": "000000000043380e", "numAttempted": 389, "tests": [{"numSolved": 387, "type": 1, "typeStr": "VISIBLE", "value": 5}, {"numSolved": 371, "type": 2, "typeStr": "HIDDEN", "value": 8}], "title": "Magical, Marvelous Tour"}, {"id": "0000000000433a3e", "numAttempted": 348, "tests": [{"numSolved": 319, "type": 1, "typeStr": "VISIBLE", "value": 10}, {"numSolved": 281, "type": 2, "typeStr": "HIDDEN", "value": 14}], "title": "Last Hit"}], "title": "Round 3 2014"}, "fullScoreboardSize": 389}